fmriprepgr/__init__.py
fmriprepgr/_html_snippets.py
fmriprepgr/_svg_edit.py
fmriprepgr/reports.py
fmriprepgr/test/__init__.py
fmriprepgr/test/test_reports.py
fmriprepgr/test/test_svg_edit.py
fmriprep_group_report-0.0.9.dist-info/LICENSE
fmriprep_group_report-0.0.9.dist-info/METADATA
fmriprep_group_report-0.0.9.dist-info/WHEEL
fmriprep_group_report-0.0.9.dist-info/entry_points.txt
fmriprep_group_report-0.0.9.dist-info/top_level.txt
fmriprep_group_report-0.0.9.dist-info/RECORD
