Metadata-Version: 2.1
Name: fmriprep-group-report
Version: 0.0.9
Summary: Make consolidated group reports from fmriprep output.
Home-page: https://github.com/nimh-comppsych/fmriprep-group-report
Author: Dylan M. Nielson
Author-email: dylan.nielson@gmail.com
License: UNKNOWN
Platform: UNKNOWN
Classifier: Programming Language :: Python :: 3
Classifier: Operating System :: POSIX
License-File: LICENSE
Requires-Dist: Click (>=8.0.3)
Requires-Dist: pybids (>=0.14)
Requires-Dist: pandas
Requires-Dist: numpy
Requires-Dist: beautifulsoup4
